App/__init__.py
App/app.py
DataStructures/AreaWay.py
DataStructures/LineWay.py
DataStructures/Node.py
DataStructures/OpenSpace.py
DataStructures/OsmObject.py
DataStructures/Relation.py
DataStructures/Way.py
DataStructures/__init__.py
ReaderWriter/Reader.py
ReaderWriter/Writer.py
ReaderWriter/__init__.py
VisibilityGraph/VisibilityGraph.py
VisibilityGraph/__init__.py
vgpedestrian-1.1.0.dist-info/METADATA
vgpedestrian-1.1.0.dist-info/WHEEL
vgpedestrian-1.1.0.dist-info/entry_points.txt
vgpedestrian-1.1.0.dist-info/top_level.txt
vgpedestrian-1.1.0.dist-info/RECORD
